swanlab/__init__.py
swanlab/__main__.py
swanlab/env.py
swanlab/error.py
swanlab/formatter.py
swanlab/package.json
swanlab/package.py
swanlab/swanlab_settings.py
swanlab/api/__init__.py
swanlab/api/base.py
swanlab/api/experiment.py
swanlab/api/group.py
swanlab/api/main.py
swanlab/api/project.py
swanlab/api/types.py
swanlab/cli/__init__.py
swanlab/cli/main.py
swanlab/cli/commands/__init__.py
swanlab/cli/commands/auth/__init__.py
swanlab/cli/commands/auth/login.py
swanlab/cli/commands/auth/logout.py
swanlab/cli/commands/auth/verify.py
swanlab/cli/commands/converter/__init__.py
swanlab/cli/commands/dashboard/__init__.py
swanlab/cli/commands/dashboard/watch.py
swanlab/cli/commands/mode/__init__.py
swanlab/cli/commands/sync/__init__.py
swanlab/converter/__init__.py
swanlab/converter/mlf/__init__.py
swanlab/converter/mlf/mlf_converter.py
swanlab/converter/tfb/__init__.py
swanlab/converter/tfb/_utils.py
swanlab/converter/tfb/tfb_converter.py
swanlab/converter/wb/__init__.py
swanlab/converter/wb/wb_converter.py
swanlab/converter/wb/wb_local_converter.py
swanlab/core_python/__init__.py
swanlab/core_python/api/experiment.py
swanlab/core_python/api/service.py
swanlab/core_python/auth/__init__.py
swanlab/core_python/auth/providers/api_key.py
swanlab/core_python/client/__init__.py
swanlab/core_python/client/model.py
swanlab/core_python/client/session.py
swanlab/core_python/uploader/__init__.py
swanlab/core_python/uploader/batch.py
swanlab/core_python/uploader/model.py
swanlab/core_python/uploader/upload.py
swanlab/core_python/uploader/thread/__init__.py
swanlab/core_python/uploader/thread/log_collector.py
swanlab/core_python/uploader/thread/start_thread.py
swanlab/core_python/uploader/thread/task_types.py
swanlab/core_python/uploader/thread/utils.py
swanlab/data/__init__.py
swanlab/data/namer.py
swanlab/data/sdk.py
swanlab/data/store.py
swanlab/data/utils.py
swanlab/data/callbacker/__init__.py
swanlab/data/callbacker/callback.py
swanlab/data/callbacker/cloud.py
swanlab-0.7.5.dist-info/METADATA
swanlab-0.7.5.dist-info/WHEEL
swanlab-0.7.5.dist-info/entry_points.txt
swanlab-0.7.5.dist-info/licenses/LICENSE
swanlab-0.7.5.dist-info/RECORD
