Metadata-Version: 2.4
Name: swanlab
Version: 0.7.5
Summary: Python library for streamlined tracking and management of AI training processes.
Project-URL: Homepage, https://swanlab.cn
Project-URL: Source, https://github.com/SwanHubX/SwanLab
Project-URL: Bug Reports, https://github.com/SwanHubX/SwanLab/issues
Project-URL: Documentation, https://docs.swanlab.cn/zh/guide_cloud/general/what-is-swanlab.html
Author-email: Cunyue <team@swanhub.co>, Feudalman <team@swanhub.co>, ZeYi Lin <team@swanhub.co>, KashiwaByte <team@swanhub.co>
License-Expression: Apache-2.0
License-File: LICENSE
Keywords: machine learning,reproducibility,visualization
Classifier: Development Status :: 3 - Alpha
Classifier: License :: OSI Approved :: Apache Software License
Classifier: Operating System :: OS Independent
Classifier: Programming Language :: Python :: 3
Classifier: Programming Language :: Python :: 3 :: Only
Classifier: Programming Language :: Python :: 3.8
Classifier: Programming Language :: Python :: 3.9
Classifier: Programming Language :: Python :: 3.10
Classifier: Programming Language :: Python :: 3.11
Classifier: Programming Language :: Python :: 3.12
Classifier: Topic :: Scientific/Engineering
Classifier: Topic :: Scientific/Engineering :: Artificial Intelligence
Classifier: Topic :: Scientific/Engineering :: Visualization
Requires-Python: >=3.8
Requires-Dist: click
Requires-Dist: nvidia-ml-py
Requires-Dist: platformdirs>=4.2.0
Requires-Dist: protobuf!=4.21.0,!=5.28.0,<7,>=3.12.0; python_version < '3.9' and sys_platform == 'linux'
Requires-Dist: protobuf!=4.21.0,!=5.28.0,<7,>=3.15.0; python_version == '3.9' and sys_platform == 'linux'
Requires-Dist: protobuf!=4.21.0,!=5.28.0,<7,>=3.19.0; python_version > '3.9' and sys_platform == 'linux'
Requires-Dist: protobuf!=4.21.0,!=5.28.0,<7,>=3.19.0; sys_platform != 'linux'
Requires-Dist: psutil>=5.0.0
Requires-Dist: pydantic~=2.0
Requires-Dist: pyecharts>=2.0.0
Requires-Dist: pyyaml
Requires-Dist: requests>=2.28.0
Requires-Dist: rich<14.0.0,>=13.6.0
Requires-Dist: setuptools
Requires-Dist: typing-extensions; python_version < '3.9'
Requires-Dist: urllib3>=1.26.0
Requires-Dist: wrapt>=1.17.0
Provides-Extra: dashboard
Requires-Dist: swanboard==0.1.9b1; extra == 'dashboard'
Provides-Extra: media
Requires-Dist: imageio[ffmpeg]; extra == 'media'
Requires-Dist: matplotlib; extra == 'media'
Requires-Dist: moviepy; extra == 'media'
Requires-Dist: numpy; extra == 'media'
Requires-Dist: pillow; extra == 'media'
Requires-Dist: rdkit; extra == 'media'
Requires-Dist: soundfile; extra == 'media'
